ALPR/__init__.py
ALPR/license_recognition.py
ALPR/test.jpg
alpr-0.0.2.dist-info/LICENSE
alpr-0.0.2.dist-info/METADATA
alpr-0.0.2.dist-info/WHEEL
alpr-0.0.2.dist-info/top_level.txt
alpr-0.0.2.dist-info/RECORD
