Metadata-Version: 2.1
Name: alpr
Version: 0.0.2
Summary: Automatic License Plate Recognition.
Home-page: https://github.com/ismail424/ALPR
Author: Ismail Sacic
Author-email: cicas03@hotmail.com
License: UNKNOWN
Platform: UNKNOWN
Classifier: Programming Language :: Python :: 3
Classifier: License :: OSI Approved :: MIT License
Classifier: Operating System :: OS Independent
Requires-Python: >=3.7
License-File: LICENSE
